<?xml version="1.0" encoding="utf-8"?>
<odoo>
    <data>


        <record id="preview_update_view_partner_form_field" model="ir.ui.view">
            <field name="name">update.res.partner.form</field>
            <field name="model">res.partner</field>
            <field name="inherit_id" ref="studio_customization.odoo_studio_res_part_f05f778e-928c-43ae-97e2-bed6ea8208a4"/>
            <field name="arch" type="xml">
                <xpath expr="//page[@name='studio_page_wTjWy']/group[@name='studio_group_wTjWy']" position="after">

                    <group string="Room details">
                        <field name="room_number"/>

                    </group>
                </xpath>
            </field>
        </record>

<!--        <record id="room_view_partner_form_field" model="ir.ui.view">-->
<!--            <field name="name">room.res.partner.form</field>-->
<!--            <field name="model">res.partner</field>-->
<!--            <field name="inherit_id" ref="base.view_partner_form" />-->
<!--            <field name="arch" type="xml">-->
<!--                <xpath expr="//form/sheet/group/group/field[@name='website']" position="after">-->
<!--                        <field name="room_number"/>-->
<!--                </xpath>-->
<!--            </field>-->
<!--        </record>-->

    </data>
</odoo>
